rmsd/__init__.py
rmsd/__main__.py
rmsd/calculate_rmsd.py
rmsd/py.typed
rmsd/version.py
rmsd-1.6.5.dist-info/licenses/LICENSE
rmsd-1.6.5.dist-info/METADATA
rmsd-1.6.5.dist-info/WHEEL
rmsd-1.6.5.dist-info/entry_points.txt
rmsd-1.6.5.dist-info/top_level.txt
rmsd-1.6.5.dist-info/RECORD
