Metadata-Version: 2.4
Name: rmsd
Version: 1.6.5
Summary: Calculate Root-mean-square deviation (RMSD) of two molecules, using rotation, in xyz or pdb format 
Project-URL: Homepage, https://github.com/charnley/rmsd
Keywords: pdb,atoms,kabsch,reordering,rotation,xyz,rmsd
Classifier: Intended Audience :: Developers
Classifier: Intended Audience :: Science/Research
Classifier: Programming Language :: Python :: 3
Classifier: Programming Language :: Python
Classifier: Topic :: Scientific/Engineering :: Chemistry
Requires-Python: >=3.10
License-File: LICENSE
Requires-Dist: numpy
Requires-Dist: scipy
Provides-Extra: qml
Requires-Dist: qmllib; extra == "qml"
Dynamic: license-file
